backend_project_fast_api/__init__.py
backend_project_fast_api/main.py
backend_project_fast_api-0.1.1.dist-info/licenses/LICENSE
backend_project_fast_api-0.1.1.dist-info/METADATA
backend_project_fast_api-0.1.1.dist-info/WHEEL
backend_project_fast_api-0.1.1.dist-info/entry_points.txt
backend_project_fast_api-0.1.1.dist-info/top_level.txt
backend_project_fast_api-0.1.1.dist-info/RECORD
